pycausal_explorer/__init__.py
pycausal_explorer/pipeline.py
pycausal_explorer/base/__init__.py
pycausal_explorer/base/_base_causal_model.py
pycausal_explorer/datasets/__init__.py
pycausal_explorer/datasets/_filenames.py
pycausal_explorer/datasets/ihdp_simulated_outcomes.py
pycausal_explorer/datasets/lalonde_nsw_jobs.py
pycausal_explorer/datasets/synthetic.py
pycausal_explorer/datasets/data/__init__.py
pycausal_explorer/forests/__init__.py
pycausal_explorer/forests/_causal_forests.py
pycausal_explorer/forests/_constants.py
pycausal_explorer/linear/__init__.py
pycausal_explorer/linear/_linear_models.py
pycausal_explorer/meta/__init__.py
pycausal_explorer/meta/_doubleML.py
pycausal_explorer/meta/_single_learner.py
pycausal_explorer/meta/_tlearner.py
pycausal_explorer/meta/_xlearner.py
pycausal_explorer/nearest_neighbors/__init__.py
pycausal_explorer/nearest_neighbors/_k_nearest_neighbors.py
pycausal_explorer/reweight/__init__.py
pycausal_explorer/reweight/_iptw.py
pycausal_explorer/reweight/_propensity_score.py
pycausal_explorer-0.2.0.dist-info/LICENSE
pycausal_explorer-0.2.0.dist-info/METADATA
pycausal_explorer-0.2.0.dist-info/WHEEL
pycausal_explorer-0.2.0.dist-info/top_level.txt
pycausal_explorer-0.2.0.dist-info/RECORD
