Metadata-Version: 2.1
Name: pycausal-explorer
Version: 0.2.0
Summary: Python causal inference modules
Home-page: https://github.com/gotolino/causal-learn
License: UNKNOWN
Platform: UNKNOWN
Classifier: Programming Language :: Python :: 3
Classifier: Programming Language :: Python :: 3.8
Classifier: Operating System :: OS Independent
License-File: LICENSE
Requires-Dist: numpy
Requires-Dist: pandas
Requires-Dist: scikit-learn
Provides-Extra: dev
Requires-Dist: pytest (>=3.7) ; extra == 'dev'
Requires-Dist: check-manifest ; extra == 'dev'
Requires-Dist: twine ; extra == 'dev'
Requires-Dist: xgboost ; extra == 'dev'
Requires-Dist: pre-commit (>=2.12) ; extra == 'dev'
Requires-Dist: pytest-cov (>=2.11) ; extra == 'dev'
Requires-Dist: flake8 (>=3.9) ; extra == 'dev'
Requires-Dist: mypy (>=0.910) ; extra == 'dev'
Requires-Dist: isort (>=5.9) ; extra == 'dev'
Requires-Dist: black (>=21.10b0) ; extra == 'dev'
